TASKS/4bitmult/src/4bitmult.v
module mult4x4_seq (
    input  wire        clk,
    input  wire        rst,
    input  wire        start,
    input  wire [3:0]  a,
    input  wire [3:0]  b,
    output reg  [7:0]  product,
    output reg         done
);

    reg [7:0] multiplicand;
    reg [3:0] multiplier;
    reg [2:0] count;

    wire [7:0] adder_out;

    // ---- Single 8-bit adder ----
    assign adder_out = product + multiplicand;

    always @(posedge clk or posedge rst) begin
        if (rst) begin
            product      <= 8'd0;
            multiplicand <= 8'd0;
            multiplier   <= 4'd0;
            count        <= 3'd0;
            done         <= 1'b0;
        end else begin
            if (start) begin
                product      <= 8'd0;
                multiplicand <= {4'd0, a}; // zero-extend
                multiplier   <= b;
                count        <= 3'd0;
                done         <= 1'b0;
            end
            else if (count < 4) begin
                if (multiplier[0])
                    product <= adder_out;   // use single adder

                multiplicand <= multiplicand << 1;
                multiplier   <= multiplier >> 1;
                count        <= count + 1;

                if (count == 3)
                    done <= 1'b1;
            end
        end
    end

endmodule

4bitmult/tb_4bitmult.v
`timescale 1ns/1ps

module tb_4bitmult;

    reg clk;
    reg rst;
    reg start;
    reg [3:0] a;
    reg [3:0] b;

    wire [7:0] product;
    wire done;

    reg [7:0] expected;   // widened expected result

    mult4x4_seq uut (
        .clk(clk),
        .rst(rst),
        .start(start),
        .a(a),
        .b(b),
        .product(product),
        .done(done)
    );

    // Clock generation (10ns period)
    always #5 clk = ~clk;

    initial begin
        $dumpfile("waveform_4bitmult.vcd");
        $dumpvars(0, tb_4bitmult);
        clk = 0;
        rst = 1;
        start = 0;
        a = 0;
        b = 0;

        #10 rst = 0;

        test_case(4'd3,  4'd5);
        test_case(4'd7,  4'd9);
        test_case(4'd15, 4'd15);
        test_case(4'd2,  4'd8);

        #50 $finish;
    end

    task test_case(input [3:0] x, input [3:0] y);
    begin
        @(posedge clk);
        a = x;
        b = y;
        start = 1;

        @(posedge clk);
        start = 0;

        wait(done);

        // Compute expected in 8-bit domain
        expected = x * y;

        $display("A=%0d B=%0d Product=%0d Expected=%0d %s",
                 x, y, product, expected,
                 (product == expected) ? "PASS" : "FAIL");

        @(posedge clk);
    end
    endtask

endmodule

4bitmult/waveform_4bitmult.vcd
$version Generated by VerilatedVcd $end
$timescale 1ps $end
 $scope module $rootio $end
 $upscope $end
 $scope module tb_4bitmult $end
  $var wire 1 . clk $end
  $var wire 1 # rst $end
  $var wire 1 $ start $end
  $var wire 4 % a [3:0] $end
  $var wire 4 & b [3:0] $end
  $var wire 8 ( product [7:0] $end
  $var wire 1 ) done $end
  $var wire 8 ' expected [7:0] $end
  $scope module uut $end
   $var wire 1 . clk $end
   $var wire 1 # rst $end
   $var wire 1 $ start $end
   $var wire 4 % a [3:0] $end
   $var wire 4 & b [3:0] $end
   $var wire 8 ( product [7:0] $end
   $var wire 1 ) done $end
   $var wire 8 * multiplicand [7:0] $end
   $var wire 4 + multiplier [3:0] $end
   $var wire 3 , count [2:0] $end
   $var wire 8 - adder_out [7:0] $end
  $upscope $end
 $upscope $end
$enddefinitions $end


#0
1#
0$
b0000 %
b0000 &
b00000000 '
b00000000 (
0)
b00000000 *
b0000 +
b000 ,
b00000000 -
0.
#5000
1.
#10000
0#
0.
#15000
1$
b0011 %
b0101 &
b00000011 *
b0101 +
b00000011 -
1.
#20000
0.
#25000
0$
b00000011 (
b00000110 *
b0010 +
b001 ,
b00001001 -
1.
#30000
0.
#35000
b00001100 *
b0001 +
b010 ,
b00001111 -
1.
#40000
0.
#45000
b00001111 (
b00011000 *
b0000 +
b011 ,
b00100111 -
1.
#50000
0.
#55000
b00001111 '
1)
b00110000 *
b100 ,
b00111111 -
1.
#60000
0.
#65000
1.
#70000
0.
#75000
1$
b0111 %
b1001 &
b00000000 (
0)
b00000111 *
b1001 +
b000 ,
b00000111 -
1.
#80000
0.
#85000
0$
b00000111 (
b00001110 *
b0100 +
b001 ,
b00010101 -
1.
#90000
0.
#95000
b00011100 *
b0010 +
b010 ,
b00100011 -
1.
#100000
0.
#105000
b00111000 *
b0001 +
b011 ,
b00111111 -
1.
#110000
0.
#115000
b00111111 '
b00111111 (
1)
b01110000 *
b0000 +
b100 ,
b10101111 -
1.
#120000
0.
#125000
1.
#130000
0.
#135000
1$
b1111 %
b1111 &
b00000000 (
0)
b00001111 *
b1111 +
b000 ,
b00001111 -
1.
#140000
0.
#145000
0$
b00001111 (
b00011110 *
b0111 +
b001 ,
b00101101 -
1.
#150000
0.
#155000
b00101101 (
b00111100 *
b0011 +
b010 ,
b01101001 -
1.
#160000
0.
#165000
b01101001 (
b01111000 *
b0001 +
b011 ,
b11100001 -
1.
#170000
0.
#175000
b11100001 '
b11100001 (
1)
b11110000 *
b0000 +
b100 ,
b11010001 -
1.
#180000
0.
#185000
1.
#190000
0.
#195000
1$
b0010 %
b1000 &
b00000000 (
0)
b00000010 *
b1000 +
b000 ,
b00000010 -
1.
#200000
0.
#205000
0$
b00000100 *
b0100 +
b001 ,
b00000100 -
1.
#210000
0.
#215000
b00001000 *
b0010 +
b010 ,
b00001000 -
1.
#220000
0.
#225000
b00010000 *
b0001 +
b011 ,
b00010000 -
1.
#230000
0.
#235000
b00010000 '
b00010000 (
1)
b00100000 *
b0000 +
b100 ,
b00110000 -
1.
