TASKS/4bitmult/src/4bitmult.v
module mult4x4_seq (
    input  wire        clk,
    input  wire        rst,
    input  wire        start,
    input  wire [3:0]  a,
    input  wire [3:0]  b,
    output reg  [7:0]  product,
    output reg         done
);

    reg [7:0] multiplicand;
    reg [3:0] multiplier;
    reg [2:0] count;

    wire [7:0] adder_out;

    // ---- Single 8-bit adder ----
    assign adder_out = product + multiplicand;

    always @(posedge clk or posedge rst) begin
        if (rst) begin
            product      <= 8'd0;
            multiplicand <= 8'd0;
            multiplier   <= 4'd0;
            count        <= 3'd0;
            done         <= 1'b0;
        end else begin
            if (start) begin
                product      <= 8'd0;
                multiplicand <= {4'd0, a}; // zero-extend
                multiplier   <= b;
                count        <= 3'd0;
                done         <= 1'b0;
            end
            else if (count < 4) begin
                if (multiplier[0])
                    product <= adder_out;   // use single adder

                multiplicand <= multiplicand << 1;
                multiplier   <= multiplier >> 1;
                count        <= count + 1;

                if (count == 3)
                    done <= 1'b1;
            end
        end
    end

endmodule

4bitmult/tb_4bitmult.v
`timescale 1ns/1ps

module tb_mult4x4_seq;

    reg clk;
    reg rst;
    reg start;
    reg [3:0] a;
    reg [3:0] b;

    wire [7:0] product;
    wire done;

    reg [7:0] expected;   // widened expected result

    mult4x4_seq uut (
        .clk(clk),
        .rst(rst),
        .start(start),
        .a(a),
        .b(b),
        .product(product),
        .done(done)
    );

    // Clock generation (10ns period)
    always #5 clk = ~clk;

    initial begin
        clk = 0;
        rst = 1;
        start = 0;
        a = 0;
        b = 0;

        // Waveform dump
        $dumpfile("wave.vcd");
        $dumpvars(0, tb_mult4x4_seq);

        #10 rst = 0;

        test_case(4'd3,  4'd5);
        test_case(4'd7,  4'd9);
        test_case(4'd15, 4'd15);
        test_case(4'd2,  4'd8);

        #50 $finish;
    end

    task test_case(input [3:0] x, input [3:0] y);
    begin
        @(posedge clk);
        a = x;
        b = y;
        start = 1;

        @(posedge clk);
        start = 0;

        wait(done);

        // Compute expected in 8-bit domain
        expected = x * y;

        $display("A=%0d B=%0d Product=%0d Expected=%0d %s",
                 x, y, product, expected,
                 (product == expected) ? "PASS" : "FAIL");

        @(posedge clk);
    end
    endtask

endmodule

4bitmult/wave.vcd
$date
	Mon Feb 16 15:54:44 2026
$end
$version
	Icarus Verilog
$end
$timescale
	1ps
$end
$scope module tb_mult4x4_seq $end
$var wire 8 ! product [7:0] $end
$var wire 1 " done $end
$var reg 4 # a [3:0] $end
$var reg 4 $ b [3:0] $end
$var reg 1 % clk $end
$var reg 8 & expected [7:0] $end
$var reg 1 ' rst $end
$var reg 1 ( start $end
$scope module uut $end
$var wire 4 ) a [3:0] $end
$var wire 4 * b [3:0] $end
$var wire 1 % clk $end
$var wire 1 ' rst $end
$var wire 1 ( start $end
$var wire 8 + adder_out [7:0] $end
$var reg 3 , count [2:0] $end
$var reg 1 " done $end
$var reg 8 - multiplicand [7:0] $end
$var reg 4 . multiplier [3:0] $end
$var reg 8 / product [7:0] $end
$upscope $end
$scope task test_case $end
$var reg 4 0 x [3:0] $end
$var reg 4 1 y [3:0] $end
$upscope $end
$upscope $end
$enddefinitions $end
$comment Show the parameter values. $end
$dumpall
$end
#0
$dumpvars
bx 1
bx 0
b0 /
b0 .
b0 -
b0 ,
b0 +
b0 *
b0 )
0(
1'
bx &
0%
b0 $
b0 #
0"
b0 !
$end
#5000
1%
#10000
0%
b101 1
b11 0
0'
#15000
b101 .
b11 +
b11 -
1(
b101 $
b101 *
b11 #
b11 )
1%
#20000
0%
#25000
b1 ,
b10 .
b110 -
b1001 +
b11 !
b11 /
0(
1%
#30000
0%
#35000
b10 ,
b1 .
b1111 +
b1100 -
1%
#40000
0%
#45000
b11 ,
b0 .
b11000 -
b100111 +
b1111 !
b1111 /
1%
#50000
0%
#55000
b1111 &
1"
b100 ,
b111111 +
b110000 -
1%
#60000
0%
#65000
b1001 1
b111 0
1%
#70000
0%
#75000
0"
b0 ,
b1001 .
b111 -
b111 +
b0 !
b0 /
1(
b1001 $
b1001 *
b111 #
b111 )
1%
#80000
0%
#85000
b1 ,
b100 .
b1110 -
b10101 +
b111 !
b111 /
0(
1%
#90000
0%
#95000
b10 ,
b10 .
b100011 +
b11100 -
1%
#100000
0%
#105000
b11 ,
b1 .
b111111 +
b111000 -
1%
#110000
0%
#115000
b111111 &
1"
b100 ,
b0 .
b1110000 -
b10101111 +
b111111 !
b111111 /
1%
#120000
0%
#125000
b1111 1
b1111 0
1%
#130000
0%
#135000
0"
b0 ,
b1111 .
b1111 -
b1111 +
b0 !
b0 /
1(
b1111 $
b1111 *
b1111 #
b1111 )
1%
#140000
0%
#145000
b1 ,
b111 .
b11110 -
b101101 +
b1111 !
b1111 /
0(
1%
#150000
0%
#155000
b10 ,
b11 .
b111100 -
b1101001 +
b101101 !
b101101 /
1%
#160000
0%
#165000
b11 ,
b1 .
b1111000 -
b11100001 +
b1101001 !
b1101001 /
1%
#170000
0%
#175000
b11100001 &
1"
b100 ,
b0 .
b11110000 -
b11010001 +
b11100001 !
b11100001 /
1%
#180000
0%
#185000
b1000 1
b10 0
1%
#190000
0%
#195000
0"
b0 ,
b1000 .
b10 -
b10 +
b0 !
b0 /
1(
b1000 $
b1000 *
b10 #
b10 )
1%
#200000
0%
#205000
b1 ,
b100 .
b100 +
b100 -
0(
1%
#210000
0%
#215000
b10 ,
b10 .
b1000 +
b1000 -
1%
#220000
0%
#225000
b11 ,
b1 .
b10000 +
b10000 -
1%
#230000
0%
#235000
b10000 &
1"
b100 ,
b0 .
b100000 -
b110000 +
b10000 !
b10000 /
1%
